model_registry/__init__.py
model_registry/_client.py
model_registry/_experiments.py
model_registry/_utils.py
model_registry/core.py
model_registry/exceptions.py
model_registry/types/__init__.py
model_registry/types/artifacts.py
model_registry/types/base.py
model_registry/types/contexts.py
model_registry/types/experiments.py
model_registry/types/options.py
model_registry/types/pager.py
model_registry/utils.py
mr_openapi/README.md
mr_openapi/__init__.py
mr_openapi/api/__init__.py
mr_openapi/api/model_registry_service_api.py
mr_openapi/api_client.py
mr_openapi/api_response.py
mr_openapi/configuration.py
mr_openapi/exceptions.py
mr_openapi/models/__init__.py
mr_openapi/models/artifact.py
mr_openapi/models/artifact_create.py
mr_openapi/models/artifact_list.py
mr_openapi/models/artifact_state.py
mr_openapi/models/artifact_type_query_param.py
mr_openapi/models/artifact_update.py
mr_openapi/models/base_artifact.py
mr_openapi/models/base_model.py
mr_openapi/models/base_resource.py
mr_openapi/models/base_resource_create.py
mr_openapi/models/base_resource_dates.py
mr_openapi/models/base_resource_list.py
mr_openapi/models/base_resource_update.py
mr_openapi/models/data_set.py
mr_openapi/models/data_set_create.py
mr_openapi/models/data_set_update.py
mr_openapi/models/doc_artifact.py
mr_openapi/models/doc_artifact_create.py
mr_openapi/models/doc_artifact_update.py
mr_openapi/models/error.py
mr_openapi/models/execution_state.py
mr_openapi/models/experiment.py
mr_openapi/models/experiment_create.py
mr_openapi/models/experiment_list.py
mr_openapi/models/experiment_run.py
mr_openapi/models/experiment_run_create.py
mr_openapi/models/experiment_run_list.py
mr_openapi/models/experiment_run_state.py
mr_openapi/models/experiment_run_status.py
mr_openapi/models/experiment_run_update.py
mr_openapi/models/experiment_state.py
mr_openapi/models/experiment_update.py
mr_openapi/models/inference_service.py
mr_openapi/models/inference_service_create.py
mr_openapi/models/inference_service_list.py
model_registry-0.3.5.dist-info/METADATA
model_registry-0.3.5.dist-info/WHEEL
model_registry-0.3.5.dist-info/RECORD
