Metadata-Version: 2.3
Name: model-registry
Version: 0.3.5
Summary: Client for Kubeflow Model Registry
License: Apache-2.0
Author: Isabella Basso do Amaral
Author-email: idoamara@redhat.com
Requires-Python: >=3.10,<4.0
Classifier: License :: OSI Approved :: Apache Software License
Classifier: Programming Language :: Python :: 3
Classifier: Programming Language :: Python :: 3.10
Classifier: Programming Language :: Python :: 3.11
Classifier: Programming Language :: Python :: 3.12
Classifier: Programming Language :: Python :: 3.13
Provides-Extra: boto3
Provides-Extra: hf
Provides-Extra: olot
Requires-Dist: aiohttp (>=3.9.5,<4.0.0)
Requires-Dist: aiohttp-retry (>=2.8.3,<3.0.0)
Requires-Dist: boto3 (>=1.37.34,<2.0.0) ; extra == "boto3"
Requires-Dist: huggingface-hub (>=0.20.1,<1.3.0) ; extra == "hf"
Requires-Dist: nest-asyncio (>=1.6.0,<2.0.0)
Requires-Dist: olot (>=0.1.6,<0.2.0) ; extra == "olot"
Requires-Dist: pydantic (>=2.7.4,<3.0.0)
Requires-Dist: python-dateutil (>=2.9.0.post0,<3.0.0)
Requires-Dist: typing-extensions (>=4.8,<5.0)
Project-URL: Homepage, https://github.com/kubeflow/model-registry
Project-URL: Issues, https://github.com/kubeflow/model-registry/issues
